borch/__init__.py
borch/graph.py
borch/module.py
borch/optimizer_collection.py
borch/random_variable.py
borch/rv_factories.py
borch/transform.py
borch/distributions/__init__.py
borch/distributions/constraint_transforms.py
borch/distributions/distribution_utils.py
borch/distributions/distributions.py
borch/distributions/kl_div.py
borch/distributions/rv_distributions.py
borch/distributions/transformations.py
borch/infer/__init__.py
borch/infer/hard_negative_mining.py
borch/infer/hmc.py
borch/infer/laplace.py
borch/infer/log_prob.py
borch/infer/model_conversion.py
borch/infer/nuts.py
borch/infer/vi.py
borch/metrics/__init__.py
borch/metrics/metrics.py
borch/metrics/rv_metrics.py
borch/metrics/uncertainty_measurements.py
borch/nn/__init__.py
borch/nn/borchify.py
borch/nn/torch_proxies.py
borch/nn/utils/__init__.py
borch/nn/utils/network_utils.py
borch/posterior/__init__.py
borch/posterior/as_prior.py
borch/posterior/automatic.py
borch/posterior/manual.py
borch/posterior/normal.py
borch/posterior/pointmass.py
borch/posterior/posterior.py
borch/utils/__init__.py
borch/utils/data.py
borch/utils/func_tools.py
borch/utils/init.py
borch/utils/module_utils.py
borch/utils/namespace_tools.py
borch/utils/numpy_utils.py
borch/utils/state_dict.py
borch/utils/testing.py
borch/utils/torch_utils.py
borch-0.1.6.dist-info/LICENSE
borch-0.1.6.dist-info/METADATA
borch-0.1.6.dist-info/WHEEL
borch-0.1.6.dist-info/top_level.txt
borch-0.1.6.dist-info/RECORD
