Metadata-Version: 2.1
Name: borch
Version: 0.1.6
Summary: Probabilistic programming using pytorch.
Author-email: Desupervised <info@desupervised.io>
License: Apache-2.0
Project-URL: Documentaion, https://borch.readthedocs.io/en/latest/
Project-URL: Issues, https://github.com/pypa/sampleproject/issues
Requires-Python: >=3.7
License-File: LICENSE
Requires-Dist: numpy>=1.17.5
Requires-Dist: scipy>=1.2.0
Requires-Dist: torch>=2.0.0
Provides-Extra: docs
Requires-Dist: matplotlib==2.2.3; extra == "docs"
Requires-Dist: nbsphinx; extra == "docs"
Requires-Dist: sphinx==2.2.2; extra == "docs"
Requires-Dist: sphinx_gallery; extra == "docs"
Requires-Dist: sphinx_rtd_theme; extra == "docs"
Requires-Dist: sphinxcontrib-bibtex<2.0.0; extra == "docs"
Requires-Dist: sphinx-versions==1.0.1; extra == "docs"
Requires-Dist: recommonmark; extra == "docs"
Requires-Dist: pillow; extra == "docs"
Requires-Dist: pytorch_lightning; extra == "docs"
Requires-Dist: torch; extra == "docs"
Requires-Dist: torchvision; extra == "docs"
Requires-Dist: torch-sparse; extra == "docs"
Requires-Dist: torch-geometric; extra == "docs"
Provides-Extra: examples
Requires-Dist: notebook; extra == "examples"
Provides-Extra: lint
Requires-Dist: ruff==0.8; extra == "lint"
Provides-Extra: test
Requires-Dist: coverage==7.6; extra == "test"
Requires-Dist: pytest-cov==6.0; extra == "test"
